sqlalchemy_cruder/__init__.py
sqlalchemy_cruder/cli.py
sqlalchemy_cruder/sqlalchemy_cruder.py
sqlalchemy_cruder-0.1.0.dist-info/DESCRIPTION.rst
sqlalchemy_cruder-0.1.0.dist-info/METADATA
sqlalchemy_cruder-0.1.0.dist-info/RECORD
sqlalchemy_cruder-0.1.0.dist-info/WHEEL
sqlalchemy_cruder-0.1.0.dist-info/entry_points.txt
sqlalchemy_cruder-0.1.0.dist-info/metadata.json
sqlalchemy_cruder-0.1.0.dist-info/top_level.txt
