Metadata-Version: 2.0
Name: sqlalchemy-cruder
Version: 0.1.0
Summary: Based on Alchemy, providing crud API for table operation.
Home-page: https://github.com/fanqingsong/sqlalchemy_cruder
Author: Lightsong
Author-email: qsfan@qq.com
License: MIT license
Keywords: sqlalchemy_cruder
Platform: UNKNOWN
Classifier: Development Status :: 2 - Pre-Alpha
Classifier: Intended Audience :: Developers
Classifier: License :: OSI Approved :: MIT License
Classifier: Natural Language :: English
Classifier: Programming Language :: Python :: 3
Classifier: Programming Language :: Python :: 3.6
Classifier: Programming Language :: Python :: 3.7
Classifier: Programming Language :: Python :: 3.8
Requires-Python: >=3.6
Requires-Dist: Click (>=7.0)
